call_flow/__init__.py
call_flow/tools/__init__.py
call_flow/tools/call_flow_tool.py
call_flow/tools/utils.py
call_flow/yamls/call_flow_tool.yaml
tests/__init__.py
tests/test_call_flow_tool.py
call_flow_cloocus_test-0.0.1.dist-info/METADATA
call_flow_cloocus_test-0.0.1.dist-info/WHEEL
call_flow_cloocus_test-0.0.1.dist-info/entry_points.txt
call_flow_cloocus_test-0.0.1.dist-info/top_level.txt
call_flow_cloocus_test-0.0.1.dist-info/RECORD
