Metadata-Version: 2.1
Name: call_flow_cloocus_test
Version: 0.0.1
Summary: Import another flow in prompt flow
